robocorp/actions/__init__.py
robocorp/actions/__main__.py
robocorp/actions/_action_context.py
robocorp/actions/_action_options.py
robocorp/actions/_args_dispatcher.py
robocorp/actions/_fixtures.py
robocorp/actions/_lint_action.py
robocorp/actions/_managed_parameters.py
robocorp/actions/_protocols.py
robocorp/actions/_request.py
robocorp/actions/_request_impl.py
robocorp/actions/_secret.py
robocorp/actions/cli.py
robocorp/actions/py.typed
robocorp_actions-0.2.3.dist-info/METADATA
robocorp_actions-0.2.3.dist-info/WHEEL
robocorp_actions-0.2.3.dist-info/RECORD
