Metadata-Version: 2.3
Name: robocorp-actions
Version: 0.2.3
Summary: Robocorp Actions
License: Apache-2.0
Author: Fabio Z.
Author-email: fabio@robocorp.com
Requires-Python: >=3.9,<4.0
Classifier: License :: OSI Approved :: Apache Software License
Classifier: Programming Language :: Python :: 3
Classifier: Programming Language :: Python :: 3.9
Classifier: Programming Language :: Python :: 3.10
Classifier: Programming Language :: Python :: 3.11
Classifier: Programming Language :: Python :: 3.12
Classifier: Programming Language :: Python :: 3.13
Requires-Dist: cryptography (>=43.0.1,<44.0.0)
Requires-Dist: robocorp-tasks (==3.1.1)
Project-URL: Repository, https://github.com/robocorp/robocorp/
